gklr/__init__.py
gklr/calcs.py
gklr/config.py
gklr/estimation.py
gklr/gklr.py
gklr/kernel_calcs.py
gklr/kernel_estimator.py
gklr/kernel_matrix.py
gklr/kernel_utils.py
gklr/logger.py
gklr/optimizer.py
gklr-0.2.0.dist-info/AUTHORS.md
gklr-0.2.0.dist-info/LICENSE
gklr-0.2.0.dist-info/METADATA
gklr-0.2.0.dist-info/WHEEL
gklr-0.2.0.dist-info/top_level.txt
gklr-0.2.0.dist-info/zip-safe
gklr-0.2.0.dist-info/RECORD
