Metadata-Version: 2.1
Name: gklr
Version: 0.2.0
Summary: Generalized Kernel Logistic Regression
Home-page: https://github.com/JoseAngelMartinB/gklr
Author: José Ángel Martín Baos
Author-email: JoseAngel.Martin@uclm.es
License: MIT License
Project-URL: Documentation, https://gklr.joseangelmartin.com/
Project-URL: Source, https://github.com/JoseAngelMartinB/gklr
Platform: any
Classifier: Development Status :: 4 - Beta
Classifier: Programming Language :: Python
Classifier: Topic :: Scientific/Engineering
Classifier: Topic :: Scientific/Engineering :: Artificial Intelligence
Classifier: Topic :: Scientific/Engineering :: Mathematics
Classifier: Intended Audience :: Science/Research
Classifier: Intended Audience :: End Users/Desktop
Classifier: Intended Audience :: Developers
Classifier: License :: OSI Approved :: MIT License
Classifier: Programming Language :: Python :: 3.7
Classifier: Programming Language :: Python :: 3.8
Classifier: Programming Language :: Python :: 3.9
Classifier: Programming Language :: Python :: 3.10
Classifier: Programming Language :: Python :: 3.11
Classifier: Programming Language :: Python :: 3.12
Requires-Python: >=3.7
License-File: LICENSE
License-File: AUTHORS.md
Requires-Dist: importlib-metadata
Requires-Dist: numpy (>=1.15.0)
Requires-Dist: scipy
Requires-Dist: pandas (>=0.16.2)
Requires-Dist: pympler
Provides-Extra: testing
Requires-Dist: setuptools ; extra == 'testing'
Requires-Dist: pytest ; extra == 'testing'
Requires-Dist: pytest-cov ; extra == 'testing'
